odoo10_addon_l10n_nl_postcodeapi-10.0.0.1.0-py2.7-nspkg.pth
odoo10_addon_l10n_nl_postcodeapi-10.0.0.1.0.dist-info/top_level.txt
odoo10_addon_l10n_nl_postcodeapi-10.0.0.1.0.dist-info/WHEEL
odoo10_addon_l10n_nl_postcodeapi-10.0.0.1.0.dist-info/RECORD
odoo10_addon_l10n_nl_postcodeapi-10.0.0.1.0.dist-info/metadata.json
odoo10_addon_l10n_nl_postcodeapi-10.0.0.1.0.dist-info/DESCRIPTION.rst
odoo10_addon_l10n_nl_postcodeapi-10.0.0.1.0.dist-info/METADATA
odoo10_addon_l10n_nl_postcodeapi-10.0.0.1.0.dist-info/namespace_packages.txt
odoo/addons/l10n_nl_postcodeapi/__manifest__.py
odoo/addons/l10n_nl_postcodeapi/__init__.py
odoo/addons/l10n_nl_postcodeapi/README.rst
odoo/addons/l10n_nl_postcodeapi/models/res_partner.py
odoo/addons/l10n_nl_postcodeapi/models/ir_config_parameter.py
odoo/addons/l10n_nl_postcodeapi/models/__init__.py
odoo/addons/l10n_nl_postcodeapi/models/res_country_state.py
odoo/addons/l10n_nl_postcodeapi/i18n/nl.po
odoo/addons/l10n_nl_postcodeapi/data/res.country.state.csv
odoo/addons/l10n_nl_postcodeapi/data/ir_config_parameter.xml
odoo/addons/l10n_nl_postcodeapi/static/description/icon.png
