Metadata-Version: 2.0
Name: odoo10-addon-l10n-nl-postcodeapi
Version: 10.0.0.1.0
Summary: Autocomplete Dutch addresses using PostcodeApi.nu
Home-page: https://github.com/OCA/l10n-netherlands
Author: UNKNOWN
Author-email: UNKNOWN
License: AGPL-3
Platform: UNKNOWN
Requires-Dist: odoo (<10.1dev,>=10.0)
Requires-Dist: odoo10-addon-partner-street-number
Requires-Dist: pyPostcode
Classifier: Programming Language :: Python :: 2.7
Classifier: Framework :: Odoo
Classifier: License :: OSI Approved :: GNU Affero General Public License v3
